LogExportTable4.py
setup.py
LogExportTable4.egg-info/PKG-INFO
LogExportTable4.egg-info/SOURCES.txt
LogExportTable4.egg-info/dependency_links.txt
LogExportTable4.egg-info/requires.txt
LogExportTable4.egg-info/top_level.txt