Metadata-Version: 2.1
Name: LogExportTable4
Version: 1.0.0
Summary: Log Export Table4
Author: SINTT
Author-email: bbhh66606@gmail.com
Requires-Dist: pyodbc
Requires-Dist: Pillow
